[
  {
    "_id": "user_id",
    "apns_token": "apns_token",
    "authorized": true,
    "device_id": "device_id",
    "gcm_token": "gcm_token",
    "phone_id": {
      "$oid": "59246c5b6195542e9b084206"
    },
    "yandex_uid": "yandex_uid"
  },
  {
    "_id": "user_id_with_plus",
    "apns_token": "apns_token",
    "authorized": true,
    "device_id": "device_id",
    "gcm_token": "gcm_token",
    "has_ya_plus": true,
    "phone_id": {
      "$oid": "59246c5b6195542e9b084206"
    },
    "yandex_uid": "yandex_uid_with_plus"
  },
  {
    "_id": "user_id_with_cashback_plus",
    "apns_token": "apns_token",
    "authorized": true,
    "device_id": "device_id",
    "gcm_token": "gcm_token",
    "has_cashback_plus": true,
    "has_ya_plus": true,
    "phone_id": {
      "$oid": "59246c5b6195542e9b084206"
    },
    "yandex_uid": "yandex_uid_with_cashback_plus"
  },
  {
    "_id": "user_id_with_disabled_new_subscription",
    "apns_token": "apns_token",
    "authorized": true,
    "device_id": "device_id",
    "gcm_token": "gcm_token",
    "has_cashback_plus": true,
    "has_ya_plus": true,
    "phone_id": {
      "$oid": "59246c5b6195542e9b084206"
    },
    "yandex_uid": "yandex_uid_with_disabled_new_subscription"
  }
]
