[
  {
    "_id": "dbid777",
    "city": "Moscow",
    "login": "taxi_dbid777",
    "name": "Taxidbid777",
    "provider_config": {
      "yandex": {
        "clid": "clid777"
      }
    }
  },
  {
    "_id": "1488",
    "city": "Moscow",
    "login": "taxi_1488",
    "name": "Taxi1488",
    "provider_config": {
      "yandex": {
        "clid": "1369"
      }
    },
    "providers": [
      "park",
      "yandex"
    ],
    "tz": 3
  },
  {
    "_id": "dbid",
    "city": "Moscow",
    "login": "dbid",
    "name": "dbid",
    "provider_config": {
      "yandex": {
        "clid": "clid"
      }
    },
    "providers": [
      "park",
      "yandex"
    ],
    "tz": 3
  },
  {
    "_id": "dbidparis",
    "city": "Paris",
    "login": "dbidparis",
    "name": "dbidparis",
    "provider_config": {
      "yandex": {
        "clid": "clid"
      }
    },
    "providers": [
      "park",
      "yandex"
    ]
  }
]
