{
  "diagnostics": {},
  "dispatch": {
    "created_ts": "2020-06-17T22:39:50+0300",
    "is_performer_assigned": false,
    "is_waybill_accepted": false,
    "is_waybill_declined": false,
    "revision": 0,
    "status": "processing",
    "updated_ts": "2020-06-17T22:39:50+0300"
  },
  "execution": {
    "paper_flow": false,
    "points": [
      {
        "address": {
          "comment": "232 - код для получения заказа\nComment restaurant 1",
          "coordinates": [
            1,
            2
          ],
          "flat": "123",
          "fullname": "Full address restaurant 1",
          "shortname": "Short address restaurant 1"
        },
        "changelog": [
          {
            "status": "pending",
            "timestamp": "2021-03-23T07:34:32.670259+00:00"
          },
          {
            "cargo_order_id": {
              "$var": "order_id"
            },
            "driver_id": "driver_id1",
            "status": "arrived",
            "timestamp": "2022-05-27T12:00:10.000000+03:00"
          }
        ],
        "claim_point_id": 1,
        "client_name": "Restaurant 1",
        "due": "2020-06-17T22:39:40+0300",
        "eta": "2021-03-23T10:46:12.875501+00:00",
        "external_order_id": "external_order_id_1",
        "is_resolved": false,
        "label": "Point A1",
        "last_status_change_ts": "2020-06-17T22:39:50+0300",
        "location": {
          "coordinates": [
            37.642979,
            55.734977
          ],
          "id": "seg3_A1"
        },
        "need_confirmation": true,
        "phones": [
          {
            "label": "Sender 1",
            "type": "source",
            "view": "main"
          }
        ],
        "point_id": "seg_1_point_1",
        "segment_id": "seg_1",
        "status": "pickuped",
        "type": "source",
        "visit_order": 1,
        "visit_status": "pending",
        "was_ready_at": "2020-06-17T22:39:50+0300"
      },
      {
        "address": {
          "comment": "Comment client 1",
          "coordinates": [
            5,
            6
          ],
          "flat": "123",
          "floor": "3",
          "fullname": "Full address client 1",
          "porch": "5",
          "shortname": "Short address client 1"
        },
        "changelog": [],
        "claim_point_id": 3,
        "client_name": "Client 1",
        "external_order_id": "external_order_id_1",
        "is_resolved": false,
        "label": "Point B1",
        "last_status_change_ts": "2020-06-17T22:39:50+0300",
        "leave_under_door": true,
        "location": {
          "coordinates": [
            37.583,
            55.8873
          ],
          "id": "seg3_A1"
        },
        "need_confirmation": true,
        "phones": [
          {
            "label": "Получатель2",
            "type": "destination",
            "view": "main"
          }
        ],
        "point_id": "seg_1_point_2",
        "segment_id": "seg_1",
        "status": "pickuped",
        "type": "destination",
        "visit_order": 2,
        "visit_status": "pending"
      }
    ],
    "segments": [
      {
        "allow_alive_batch_v1": false,
        "claim_id": "claim_uuid_1",
        "client_info": {
          "payment_info": {
            "method_id": "corp-5e36732e2bc54e088b1466e08e31c486",
            "type": "corp"
          },
          "user_id": "taxi_user_id_1"
        },
        "corp_client_id": "5e36732e2bc54e088b1466e08e31c486",
        "custom_context": {
          "entrances_photo_urls": [
            "url_1",
            "url_2"
          ],
          "order_items": [
            {
              "item_id": "1",
              "type": "some_type"
            }
          ],
          "place_id": 1,
          "promise_max_at": "2022-07-18T11:37:44+03:00",
          "promise_min_at": "2022-07-18T11:27:44+03:00"
        },
        "emergency_phone_id": "emergency_phone_id",
        "id": "seg_1",
        "status": "pickuped",
        "zone_id": "moscow"
      }
    ],
    "state_version": "v0_2",
    "taxi_order_info": {
      "order_id": {
        "$var": "order_id"
      },
      "performer_info": {
        "car_color": "белый",
        "car_id": "0b0ae3c95cc14657b63eeca58bf14852",
        "car_model": "LADA (ВАЗ) Granta",
        "car_number": "К154ЕУ126",
        "driver_id": "driver_id1",
        "name": "Резник Юрий Вячеславович",
        "park_id": "park_id1",
        "park_name": "Премьер",
        "park_org_name": "ИП Акопян Марат Владимирович",
        "phone_pd_id": "7930a74c2aa64f71b96dff9a91ea0b81",
        "tariff_class": "courier"
      }
    }
  },
  "segments": [
    {
      "allow_alive_batch_v1": false,
      "allow_batch": false,
      "client_info": {
        "payment_info": {
          "method_id": "corp-1234",
          "type": "corp"
        }
      },
      "employer": "eats",
      "id": "seg_1",
      "items": [
        {
          "dropoff_point": "seg_1_point_2",
          "item_id": "c8979166-e428-43be-8b37-5ea1c958debb",
          "pickup_point": "seg_1_point_1",
          "quantity": 1,
          "return_point": "seg_1_point_5",
          "size": {
            "height": 0.1,
            "length": 0.1,
            "width": 0.1
          },
          "title": "Item title 1",
          "weight": 15
        },
        {
          "dropoff_point": "seg_1_point_4",
          "item_id": "c000166e42843be8b375ea1c958debb",
          "pickup_point": "seg_1_point_3",
          "quantity": 2,
          "return_point": "seg_1_point_5",
          "size": {
            "height": 0.1,
            "length": 0.1,
            "width": 0.1
          },
          "title": "Item title 2",
          "weight": 15
        }
      ],
      "locations": [
        {
          "coordinates": [
            37.583,
            55.9873
          ],
          "id": "seg_1_loc_2"
        },
        {
          "coordinates": [
            37.583,
            55.8873
          ],
          "id": "seg_1_loc_3"
        },
        {
          "coordinates": [
            37.593,
            55.3873
          ],
          "id": "seg_1_loc_4"
        },
        {
          "coordinates": [
            37.642979,
            55.734977
          ],
          "id": "seg_1_loc_1"
        }
      ],
      "performer_requirements": {
        "door_to_door": true,
        "special_requirements": {
          "virtual_tariffs": []
        },
        "taxi_classes": [
          "express"
        ]
      },
      "points": [
        {
          "contact": {
            "name": "contact_loc_source",
            "personal_phone_id": "+70000000001_id"
          },
          "location_id": "seg_1_loc_1",
          "point_id": "seg_1_point_1",
          "type": "pickup",
          "visit_order": 1
        },
        {
          "contact": {
            "name": "contact_loc_destination",
            "personal_phone_id": "+70000000002_id"
          },
          "location_id": "seg_1_loc_2",
          "point_id": "seg_1_point_2",
          "type": "dropoff",
          "visit_order": 2
        }
      ],
      "zone_id": "moscow"
    }
  ],
  "waybill": {
    "external_ref": "waybill-ref",
    "items": [],
    "points": [
      {
        "point_id": "seg_1_point_1",
        "segment_id": "seg_1",
        "visit_order": 1
      },
      {
        "point_id": "seg_1_point_2",
        "segment_id": "seg_1",
        "visit_order": 3
      }
    ],
    "router_id": "router",
    "special_requirements": {
      "virtual_tariffs": [
        {
          "class": "cargo",
          "special_requirements": [
            {
              "id": "cargo_eds"
            }
          ]
        }
      ]
    },
    "taxi_order_requirements": {
      "taxi_classes": [
        "courier",
        "express"
      ]
    }
  }
}
